neurosec/__init__.py
neurosec/neurosec.py
neurosec/neurosec_node.py
neurosec/models/yolo.fbz
neurosec/models/yolo_face.fbz
neurosec/templates/index.html
neurosec-1.0.0.dist-info/LICENSE
neurosec-1.0.0.dist-info/METADATA
neurosec-1.0.0.dist-info/WHEEL
neurosec-1.0.0.dist-info/top_level.txt
neurosec-1.0.0.dist-info/RECORD
