Metadata-Version: 2.1
Name: neurosec
Version: 1.0.0
Summary: A neuromorphic inference wrapper for the popular VidGear video processing library.
Home-page: https://stdp.io
Author: stdp
Author-email: info@stdp.io
License: Apache License 2.0
Project-URL: Bug Tracker, https://github.com/stdp/neurosec/issues
Keywords: stdp,stdp.io,neuromorphic,security,akida,brainchip,camgear,vidgear,streaming
Platform: UNKNOWN
Classifier: Programming Language :: Python :: 3
Classifier: License :: OSI Approved :: MIT License
Classifier: Operating System :: OS Independent
Requires-Python: >=3.7
License-File: LICENSE
Requires-Dist: vidgear[core]
Requires-Dist: numpy
Requires-Dist: akida
Requires-Dist: akida-models
Requires-Dist: opencv-python
Requires-Dist: imutils
Requires-Dist: flask
